sdk/buckets.py
sdk/gen/__init__.py
sdk/gen/pubsub/__init__.py
sdk/gen/pubsub/v2/__init__.py
sdk/gen/pubsub/v2/pubsub_pb2.py
sdk/gen/pubsub/v2/pubsub_pb2_grpc.py
sdk/gen/storage/__init__.py
sdk/gen/storage/v2/__init__.py
sdk/gen/storage/v2/storage_pb2.py
sdk/gen/storage/v2/storage_pb2_grpc.py
veetwo_client-0.1.0.dist-info/licenses/LICENSE
veetwo_client-0.1.0.dist-info/METADATA
veetwo_client-0.1.0.dist-info/WHEEL
veetwo_client-0.1.0.dist-info/top_level.txt
veetwo_client-0.1.0.dist-info/RECORD
