Metadata-Version: 2.4
Name: veetwo-client
Version: 0.1.0
Summary: Nitric Python Client
License: Apache-2.0
Requires-Python: >=3.10
License-File: LICENSE
Requires-Dist: grpcio
Requires-Dist: grpcio-tools
Requires-Dist: protobuf
Dynamic: license-file
